Workbook
Name FechaControl: '[1]Tabla (H)'!$P$6:$P$25
Name ImpactoRiesgo: 'Información'!$I$9:$K$9
Name ListaFechas: #REF!
Name ProbabilidadRiesgo: 'Información'!$H$6:$H$8
Name EstadoRiesgos: 'Información'!$B$18:$B$21
Name Criticidad: 'Información'!$B$4:$B$6
Name ListaFechas: #REF!
Name PrioridadRiesgo: 'Información'!$H$6:$H$8
Name Estado: 'Información'!$B$9:$B$12
Name MatrizRiesgo: 'Información'!$I$6:$K$8

Sheet Información
O2: Ejemplo
B3: Tabla de Criticidad | P3: Se ve con una lista (ProbabilidadRiesgo) | Q3: Se ve con una lista (ImpactoRiesgo)
B4: Alto | C4: 3 | G4: Matriz de Riesgos - Criticidad | O4: Criticidad | P4: Probabilidad | Q4: Impacto
B5: Medio | C5: 2 | H5: Probabilidad | O5: {=INDEX(MatrizRiesgo,MATCH(P5,ProbabilidadRiesgo,0),MATCH(Q5,ImpactoRiesgo,0))} -> 1 | P5: Alta | Q5: Alto
B6: Bajo | C6: 1 | H6: Alta | I6: 4 | J6: 2 | K6: 1 | O6: {=INDEX(MatrizRiesgo,MATCH(P6,ProbabilidadRiesgo,0),MATCH(Q6,ImpactoRiesgo,0))} -> 3 | P6: Media | Q6: Alto
H7: Media | I7: 7 | J7: 5 | K7: 3 | O7: {=INDEX(MatrizRiesgo,MATCH(P7,ProbabilidadRiesgo,0),MATCH(Q7,ImpactoRiesgo,0))} -> 9 | P7: Baja | Q7: Bajo
B8: Estado | H8: Baja | I8: 9 | J8: 8 | K8: 6 | O8: {=INDEX(MatrizRiesgo,MATCH(P8,ProbabilidadRiesgo,0),MATCH(Q8,ImpactoRiesgo,0))} -> 7 | P8: Media | Q8: Bajo
B9: Abierto | I9: Bajo | J9: Medio | K9: Alto | L9: Impacto | O9: {=INDEX(MatrizRiesgo,MATCH(P9,ProbabilidadRiesgo,0),MATCH(Q9,ImpactoRiesgo,0))} -> 4 | P9: Alta | Q9: Bajo
B10: Cerrado | O10: {=INDEX(MatrizRiesgo,MATCH(P10,ProbabilidadRiesgo,0),MATCH(Q10,ImpactoRiesgo,0))} -> 7 | P10: Media | Q10: Bajo
B11: Eliminado | O11: {=INDEX(MatrizRiesgo,MATCH(P11,ProbabilidadRiesgo,0),MATCH(Q11,ImpactoRiesgo,0))} -> 9 | P11: Baja | Q11: Bajo
B12: Problema | G12: Tratamiento de Riesgos - Acciones | O12: {=INDEX(MatrizRiesgo,MATCH(P12,ProbabilidadRiesgo,0),MATCH(Q12,ImpactoRiesgo,0))} -> 4 | P12: Alta | Q12: Bajo
G13: Criticidad = Impacto * Probabilidad
G14: 1, 2 y 3 | H14: : Mayor prioridad, atención obligada, acción inmediata
G15: 4, 5, 6, 7 y 8 | H15: : Prioridad media, decidir entre:
H16: Plan de mitigación, si relación costo/beneficio es adecuada
B17: Estado Riesgos | H17: Plan de contingencia, si relación costo/beneficio no es adecuada
B18: Pendiente | G18: 9 | H18: Baja prioridad y monitorear Riesgo
B19: Cerrado
B20: Eliminado
B21: Problema

Sheet Información del Documento
A2: Información del documento
A3: Registro y análisis de riesgos potenciales para la Plataforma CORE Valparaíso, incluyendo impacto, probabilidad y plan de respuesta para garantizar el cumplimiento del Product Goal en 6 Sprints.
A4: Nombre Archivo
A5: Registro de Riesgos Proyecto.xlsx
A7: Historial Estructura Documento
A8: Fecha | B8: Autor / Responsable | C8: Versión | D8: Descripción
A9: 45935 | B9: Gestión de Proyectos y Calidad | C9: 1.0 | D9: Se comienza a trabajar en el documento
A12: Historial Contenido Documento y Bitácora
A13: Fecha | B13: Autor / Responsable | C13: Versión | D13: Descripción
A14: 45970 | B14: Pedro Pablo Vergara Gonzalez | C14: 1.0 | D14: Se termina de registrar los riesgos
A15: 45971 | B15: Jorge Erasmo Sepúlveda Farias | C15: 45658 | D15: Se comienza con la matriz de impacto
A16: 45972 | B16: Génesis Paulina Contreras Vargas | C16: 45689 | D16: Se termina con la matriz de impacto y probabilidad
A17: 45976 | B17: Pedro Pablo Vergara Gonzalez | C17: 45717 | D17: Se corrigen detalles de la matriz

Sheet Registro de Riesgos
A1: Registro de Riesgos
A2: ID | B2: Fecha Creación | C2: Tipo | D2: Riesgo (Evento) | E2: Causa | F2: Efecto | G2: Probabilidad Ocurrencia | H2: Impacto | I2: Probabilidad | J2: Impacto | K2: Criticidad | L2: Respuesta (Evitar, Transferir, Mitigar) | M2: Responsable | N2: Fecha de Compromiso | O2: Estado | P2: Comentarios
A3: 1 | B3: 45968 | C3: Calendario | D3: Retraso en el inicio del proyecto por falta de alineación del equipo. | E3: No se definieron claramente las tareas iniciales y responsabilidades. | F3: Plazo | G3: Medio | H3: Alto | I3: 4 | J3: 3 | K3: {=INDEX(Matriz!$D$6:$H$10,I3,J3)} -> Medio | L3: Mitigar: Reunión de kickoff con definición de roles y objetivos claros. | M3: Scrum Master | N3: 45876 | O3: Cerrado | P3: Reunión inicial agendada para alinear tareas.
A4: 2 | B4: 45968 | C4: Requisitos | D4: Requerimientos incompletos entregados por el cliente. | E4: Falta de reuniones de levantamiento con los usuarios finales. | F4: Alcance | G4: Alto | H4: Medio | I4: 4 | J4: 3 | K4: {=INDEX(Matriz!$D$6:$H$10,I4,J4)} -> Medio | L4: Evitar: Validar requerimientos mediante minutas de comisión y aprobaciones formales. | M4: Product Owner | N4: 45877 | O4: Cerrado | P4: Reuniones adicionales programadas para clarificar requerimientos.
A5: 3 | B5: 45968 | C5: Tecnico | D5: Fallo en la conexión entre el backend y la base de datos MariaDB. | E5: Configuración incorrecta del archivo .env o credenciales desactualizadas. | F5: Calidad | G5: Bajo | H5: Medio | I5: 3 | J5: 1 | K5: {=INDEX(Matriz!$D$6:$H$10,I4,J4)} -> Medio | L5: Mitigar: Crear checklist de conexión y revisar variables de entorno antes de cada despliegue. | M5: Scrum Master | N5: 45878 | O5: Pendiente | P5: Configuración ajustada para entorno estable.
A6: 4 | B6: 45968 | C6: Seguridad | D6: Acceso no autorizado al panel de administración. | E6: Falta de validación de roles y permisos en el sistema. | F6: Calidad | G6: Medio | H6: Medio | I6: 4 | J6: 2 | K6: {=INDEX(Matriz!$D$6:$H$10,I4,J4)} -> Medio | L6: Mitigar: Definir vistas por roles en la plataforma. | M6: Equipo de Desarrollo | N6: 45879 | O6: Cerrado | P6: Se revisan roles y permisos en validación.
A7: 5 | B7: 45968 | C7: Comunicacion | D7: Información inconsistente entre miembros del equipo. | E7: Falta de registro de acuerdos en minutas. | F7: Plazo | G7: Bajo | H7: Medio | I7: 4 | J7: 2 | K7: {=INDEX(Matriz!$D$6:$H$10,I7,J7)} -> Bajo | L7: Mitigar: Establecer canal oficial de comunicación y revisar minutas en cada reunión semanal. | M7: Scrum Master | N7: 45881 | O7: Cerrado | P7: Se documentan minutas y avances en comiciones.
A8: 6 | B8: 45968 | C8: Calidad | D8: Entregable intermedio sin cumplir los criterios de aceptación. | E8: Revisión superficial de funcionalidades antes de presentar avances. | F8: Calidad | G8: Medio | H8: Medio | I8: 5 | J8: 3 | K8: {=INDEX(Matriz!$D$6:$H$10,I8,J8)} -> Medio | L8: Mitigar: Crear checklist de validación previa a cada revisión de sprint. | M8: Equipo de Desarrollo | N8: 45882 | O8: Cerrado | P8: Se documentan acuerdos y avances en minutas.
A9: 7 | B9: 45968 | C9: Alcanse | D9: Solicitud de nuevas funcionalidades fuera del backlog aprobado. | E9: Cambios de prioridades del cliente sin control de alcance. | F9: Alcance | G9: Alto | H9: Medio | I9: 4 | J9: 3 | K9: {=INDEX(Matriz!$D$6:$H$10,I9,J9)} -> Medio | L9: Evitar: Formalizar control de cambios y documentar ajustes con firma del cliente. | M9: Product Owner | N9: 45883 | O9: Cerrado | P9: Se ajustan prioridades del backlog según impacto.
A10: 8 | B10: 45968 | C10: Infraestructura | D10: Caída del servidor local durante pruebas internas. | E10: Falta de mantenimiento o capacidad insuficiente del servidor. | F10: Plazo | G10: Medio | H10: Medio | I10: 4 | J10: 3 | K10: {=INDEX(Matriz!$D$6:$H$10,I10,J10)} -> Medio | L10: Transferir: Migrar pruebas a entorno en la nube con backup automático. | M10: Equipo de desarrollo | N10: 45884 | O10: Problema | P10: Se programó para un facil mantenimiento.
A11: 9 | B11: 45968 | C11: Gestion | D11: Desviación del cronograma de la Carta Gantt. | E11: Mala estimación del esfuerzo en tareas críticas. | F11: Plazo | G11: Medio | H11: Medio | I11: 3 | J11: 3 | K11: {=INDEX(Matriz!$D$6:$H$10,I11,J11)} -> Alto | L11: Mitigar: Replanificar actividades con base en la velocidad real del equipo. | M11: Equipo de Desarrollo | N11: 45885 | O11: Problema | P11: Seguimiento activo del cronograma y recursos.
A12: 10 | B12: 45968 | C12: Tecnico | D12: Fallo en el despliegue de la aplicación en el servidor de pruebas. | E12: Configuración incorrecta del entorno o dependencias faltantes. | F12: Plazo | G12: Medio | H12: Medio | I12: 3 | J12: 2 | K12: {=INDEX(Matriz!$D$6:$H$10,I12,J12)} -> Medio | L12: Mitigar: Automatizar despliegues con scripts validados y verificación de dependencias. | M12: Scrum Master | N12: 45886 | O12: Cerrado | P12: Configuración ajustada para entorno estable mediante GitHub.
A13: 11 | B13: 45968 | C13: Requisitos | D13: Historias de usuario con criterios de aceptación ambiguos. | E13: Falta de revisión conjunta entre el equipo y el cliente. | F13: Calidad | G13: Medio | H13: Medio | I13: 3 | J13: 2 | K13: {=INDEX(Matriz!$D$6:$H$10,I13,J13)} -> Medio | L13: Evitar: Validar criterios de aceptación en reuniones de refinamiento. | M13: Equipo de desarrollo | N13: 45887 | O13: Cerrado | P13: Levantamiento adicional en curso con usuarios.
A14: 12 | B14: 45968 | C14: Gestion | D14: Sobrecarga de tareas en un sprint por mala estimación de esfuerzo. | E14: Falta de experiencia previa en proyectos similares. | F14: Plazo | G14: Medio | H14: Medio | I14: 3 | J14: 2 | K14: {=INDEX(Matriz!$D$6:$H$10,I14,J14)} -> Medio | L14: Mitigar: Revisar la capacidad del equipo antes de planificar cada sprint. | M14: Product Owner | N14: 45888 | O14: Cerrado | P14: Es nesesario el apoyo de informaticos del core para obtener un servidor de pruebas.
A15: 13 | B15: 45968 | C15: Seguridad | D15: Contraseñas almacenadas en texto plano en la base de datos. | E15: Falta de cifrado en el módulo de autenticación. | F15: Calidad | G15: Alto | H15: Medio | I15: 3 | J15: 5 | K15: {=INDEX(Matriz!$D$6:$H$10,I15,J15)} -> Muy Alto | L15: Mitigar: Implementar hash seguro. | M15: Equipo de Desarrollo | N15: 45890 | O15: Cerrado | P15: MFA implementada y revisión de permisos en curso.
A16: 14 | B16: 45968 | C16: Integracion | D16: Incompatibilidad entre versiones de librerías. | E16: Actualizaciones sin revisión de impacto. | F16: Plazo | G16: Bajo | H16: Muy Alto | I16: 4 | J16: 2 | K16: {=INDEX(Matriz!$D$6:$H$10,I16,J16)} -> Bajo | L16: Mitigar: Documentar dependencias y usar control de versiones en composer.json. | M16: Equipo de Desarrollo | N16: 45891 | O16: Cerrado | P16: Actualizaciones planificadas con control de versiones.
A17: 15 | B17: 45968 | C17: Infraestructura | D17: Fallo de conexión al servidor por saturación de red. | E17: Pruebas concurrentes sin planificación de carga. | F17: Plazo | G17: Medio | H17: Medio | I17: 4 | J17: 2 | K17: {=INDEX(Matriz!$D$6:$H$10,I17,J17)} -> Bajo | L17: Transferir: Aumentar recursos de red y programar pruebas fuera de horario laboral. | M17: Equipo de Desarrollo | N17: 45892 | O17: Problema | P17: Ejecución de pruebas técnicas en seguimiento.
A18: 16 | B18: 45968 | C18: Comunicacion | D18: Duplicación de tareas por falta de sincronización entre miembros. | E18: Falta de canales de comunicación y división de tareas. | F18: Plazo | G18: Medio | H18: Medio | I18: 4 | J18: 2 | K18: {=INDEX(Matriz!$D$6:$H$10,I18,J18)} -> Bajo | L18: Mitigar: Crear planilla en conjunto con las tareas designadas a cada miembro del equipo. | M18: Scrum Master | N18: 45893 | O18: Problema | P18: Se reforzó comunicación diaria entre el equipos.
... A74: 72 | B74: 45968 | C74: Gestion | D74: Falta de documentación del proceso de mantenimiento post entrega. | E74: No se define responsable de soporte tras implementación. | F74: Alcance | G74: Medio | H74: Medio | I74: 3 | J74: 2 | K74: {=INDEX(Matriz!$D$6:$H$10,I74,J74)} -> Medio | L74: Mitigar: Crear plan de soporte y manual de mantenimiento con responsables definidos. . | M74: Scrum Master | N74: 45979 | O74: Cerrado | P74: Manuales de usuarios y contacto de soporte propio.
E76: 45968 | Q76: 45896
E77: 45968 | Q77: 45897
E78: 45968 | Q78: 45898
E79: 45968 | F79: Técnico | I79: Costo | J79: Muy Alto | K79: Muy Alto | Q79: 45899 | R79: Pendiente
E80: 45968 | F80: Seguridad | I80: Plazo | J80: Alto | K80: Alto | Q80: 45900 | R80: Cerrado
E81: 45968 | F81: Equipo de Trabajo | I81: Alcance | J81: Medio | K81: Medio | Q81: 45901 | R81: Eliminado
E82: 45968 | F82: Calendario | I82: Calidad | J82: Bajo | K82: Bajo | Q82: 45902 | R82: Problema
E83: 45968 | F83: Costos | J83: Muy Bajo | K83: Muy Bajo | Q83: 45903
E84: 45968 | F84: Clientes y Stakeholders | Q84: 45904
E85: 45968 | Q85: 45905

Sheet Matriz
D4: Impacto
C5: Probabilidad | D5: Muy Bajo | E5: Bajo | F5: Medio | G5: Alto | H5: Muy Alto
C6: Muy Alto | D6: Medio | E6: Alto | F6: Alto | G6: Muy Alto | H6: Muy Alto
C7: Alto | D7: Medio | E7: Medio | F7: Alto | G7: Muy Alto | H7: Muy Alto
C8: Medio | D8: Bajo | E8: Medio | F8: Alto | G8: Alto | H8: Muy Alto
C9: Bajo | D9: Bajo | E9: Bajo | F9: Medio | G9: Alto | H9: Alto
C10: Muy Bajo | D10: Bajo | E10: Bajo | F10: Medio | G10: Medio | H10: Alto

Sheet Matriz Impacto y Probabilidad
D4: Impacto
C5: Probabilidad | D5: Muy Bajo | E5: Bajo | F5: Medio | G5: Alto | H5: Muy Alto
C6: Muy Alto | D6: Medio | E6: Alto | F6: Alto | G6: Muy Alto | H6: Muy Alto
C7: Alto | D7: Medio | E7: Medio | F7: Alto | G7: Muy Alto | H7: Muy Alto
C8: Medio | D8: Bajo | E8: Medio | F8: Alto | G8: Alto | H8: Muy Alto
C9: Bajo | D9: Bajo | E9: Bajo | F9: Medio | G9: Alto | H9: Alto
C10: Muy Bajo | D10: Bajo | E10: Bajo | F10: Medio | G10: Medio | H10: Alto
